calita/__init__.py
calita/__main__.py
calita/manager_agent.py
calita/run_app.py
calita/web_agent.py
calita/manager_sub_agents/final_result_agent.py
calita/manager_sub_agents/mcp_tool_agent.py
calita/manager_sub_agents/task_plan_agent.py
calita/mcp_creation/code_runner_e2b.py
calita/mcp_creation/mcp_brainstorm.py
calita/mcp_creation/mcp_creation_agent.py
calita/mcp_creation/mcp_creation_agent_pro.py
calita/mcp_creation/mcp_registry.py
calita/mcp_creation/research_agent.py
calita/mcp_creation/script_generator.py
calita/tools/fast_mcp_sandbox.py
calita/tools/mcp_box.py
calita/tools/mcp_pypi_search.py
calita/utils/__init__.py
calita/utils/mcp_config_loader.py
calita/utils/model_client.py
calita/utils/utils.py
calita-0.4.3.dist-info/METADATA
calita-0.4.3.dist-info/WHEEL
calita-0.4.3.dist-info/entry_points.txt
calita-0.4.3.dist-info/RECORD
