Metadata-Version: 2.4
Name: calita
Version: 0.4.3
Summary: Alita with Sandbox and Dynamic MCP Box
Requires-Python: >=3.13
Requires-Dist: anthropic>=0.54.0
Requires-Dist: colorlog>=6.9.0
Requires-Dist: e2b-code-interpreter>=1.5.2
Requires-Dist: langchain-mcp-adapters>=0.1.4
Requires-Dist: langgraph>=0.3.21
Requires-Dist: litellm>=1.74.8
Requires-Dist: mcp>=1.12.1
Requires-Dist: openai>=1.0.0
Requires-Dist: pyyaml>=5.4.0
Requires-Dist: requests>=2.25.0
Requires-Dist: urllib3>=1.26.0
